Metadata-Version: 2.1
Name: github-info.py
Version: 1.0.0
Summary: A GitHub API wrapper that allows you to get info on users and organisations
Home-page: https://github.com/cxllm/github-info.py
Author: Callum
Author-email: me@cxllm.xyz
License: UNKNOWN
Keywords: github,api,git,github api
Platform: UNKNOWN
Classifier: Development Status :: 4 - Beta
Classifier: License :: Freely Distributable
Classifier: Operating System :: OS Independent
Classifier: Programming Language :: Python :: 3
Classifier: Topic :: Utilities
